resume/__init__.py
resume/cli.py
resume/data.py
resume/commands/__init__.py
resume/commands/contact.py
resume/commands/education.py
resume/commands/info.py
resume/commands/projects.py
resume/commands/skills.py
resume/commands/summary.py
resume/commands/work_exp.py
resume/utils/__init__.py
resume/utils/helpers.py
sheikh_huzaif_resume-1.0.3.dist-info/licenses/LICENSE
sheikh_huzaif_resume-1.0.3.dist-info/METADATA
sheikh_huzaif_resume-1.0.3.dist-info/WHEEL
sheikh_huzaif_resume-1.0.3.dist-info/entry_points.txt
sheikh_huzaif_resume-1.0.3.dist-info/top_level.txt
sheikh_huzaif_resume-1.0.3.dist-info/RECORD
