Metadata-Version: 2.4
Name: sheikh-huzaif-resume
Version: 1.0.3
Summary: A CLI tool to present my CV
Author-email: Sheikh Huzaif <sheikhhuzaif007@gmail.com>
License-Expression: MIT
Keywords: cli,tool,terminal,resume,cv
Classifier: Development Status :: 3 - Alpha
Classifier: Intended Audience :: Developers
Classifier: Programming Language :: Python :: 3
Classifier: Programming Language :: Python :: 3.8
Classifier: Programming Language :: Python :: 3.9
Classifier: Programming Language :: Python :: 3.10
Classifier: Programming Language :: Python :: 3.11
Requires-Python: >=3.8
License-File: LICENSE
Requires-Dist: typer[all]==0.9.0
Requires-Dist: rich==13.7.0
Requires-Dist: questionary==2.0.1
Requires-Dist: pyfiglet==1.0.2
Dynamic: license-file
